discord_raid_coordinator-0.4.2.dist-info/DESCRIPTION.rst
discord_raid_coordinator-0.4.2.dist-info/METADATA
discord_raid_coordinator-0.4.2.dist-info/RECORD
discord_raid_coordinator-0.4.2.dist-info/WHEEL
discord_raid_coordinator-0.4.2.dist-info/entry_points.txt
discord_raid_coordinator-0.4.2.dist-info/metadata.json
discord_raid_coordinator-0.4.2.dist-info/top_level.txt
raid_coordinator/__init__.py
raid_coordinator/_version.py
raid_coordinator/bot.py
raid_coordinator/__pycache__/__init__.cpython-35.pyc
raid_coordinator/__pycache__/_version.cpython-35.pyc
raid_coordinator/__pycache__/bot.cpython-35.pyc
