Metadata-Version: 2.0
Name: discord-raid-coordinator
Version: 0.4.2
Summary: A discord bot for coordinating pokemon go raids.
Home-page: UNKNOWN
Author: Daniel DeSousa
Author-email: discord-raid-coordinator@daniel.desousa.cc
License: UNLICENSE
Platform: any
Classifier: Programming Language :: Python :: 3.5
Classifier: Programming Language :: Python :: 3.6
Requires-Dist: discord.py (>=0.16.8)
Requires-Dist: pytz (>=2017.2)
Provides-Extra: test
Requires-Dist: hypothesis (>=3.16.0); extra == 'test'
